cv2-stubs/__init__.pyi
cv2-stubs/_stubs_utils.pyi
cv2-stubs/classes.pyi
cv2-stubs/constants.pyi
cv2-stubs/functions.pyi
cv2-stubs/py.typed
cv2-stubs/modules/__init__.pyi
cv2-stubs/modules/aruco.pyi
cv2-stubs/modules/barcode.pyi
cv2-stubs/modules/bgsegm.pyi
cv2-stubs/modules/bioinspired.pyi
cv2-stubs/modules/ccm.pyi
cv2-stubs/modules/colored_kinfu.pyi
cv2-stubs/modules/cuda.pyi
cv2-stubs/modules/data.pyi
cv2-stubs/modules/datasets.pyi
cv2-stubs/modules/detail.pyi
cv2-stubs/modules/dnn.pyi
cv2-stubs/modules/dnn_superres.pyi
cv2-stubs/modules/dpm.pyi
cv2-stubs/modules/dynafu.pyi
cv2-stubs/modules/error.pyi
cv2-stubs/modules/face.pyi
cv2-stubs/modules/fisheye.pyi
cv2-stubs/modules/flann.pyi
cv2-stubs/modules/ft.pyi
cv2-stubs/modules/hfs.pyi
cv2-stubs/modules/img_hash.pyi
cv2-stubs/modules/intensity_transform.pyi
cv2-stubs/modules/ipp.pyi
cv2-stubs/modules/large_kinfu.pyi
cv2-stubs/modules/legacy.pyi
cv2-stubs/modules/line_descriptor.pyi
cv2-stubs/modules/linemod.pyi
cv2-stubs/modules/load_config_py3.pyi
cv2-stubs/modules/mat_wrapper.pyi
cv2-stubs/modules/mcc.pyi
cv2-stubs/modules/ml.pyi
cv2-stubs/modules/motempl.pyi
cv2-stubs/modules/multicalib.pyi
cv2-stubs/modules/ocl.pyi
cv2-stubs/modules/ogl.pyi
cv2-stubs/modules/omnidir.pyi
cv2-stubs/modules/optflow.pyi
cv2-stubs/modules/parallel.pyi
cv2-stubs/modules/phase_unwrapping.pyi
cv2-stubs/modules/plot.pyi
cv2-stubs/modules/ppf_match_3d.pyi
cv2-stubs/modules/qt.pyi
cv2-stubs/modules/quality.pyi
cv2-stubs/modules/rapid.pyi
cv2-stubs/modules/reg.pyi
cv2-stubs/modules/rgbd.pyi
cv2-stubs/modules/saliency.pyi
cv2-stubs/modules/samples.pyi
cv2-stubs/modules/segmentation.pyi
cv2-stubs/modules/stereo.pyi
cv2-stubs/modules/structured_light.pyi
cv2-stubs/modules/text.pyi
cv2-stubs/modules/version.pyi
cv2-stubs/modules/videoio_registry.pyi
cv2-stubs/modules/videostab.pyi
cv2-stubs/modules/wechat_qrcode.pyi
cv2-stubs/modules/xfeatures2d.pyi
cv2-stubs/modules/xphoto.pyi
cv2-stubs/modules/gapi/__init__.pyi
opencv_stubs-0.1.1.dist-info/METADATA
opencv_stubs-0.1.1.dist-info/WHEEL
opencv_stubs-0.1.1.dist-info/licenses/LICENSE
opencv_stubs-0.1.1.dist-info/RECORD
