Metadata-Version: 2.4
Name: opencv-stubs
Version: 0.1.1
Summary: Unofficial stubs for the opencv-python package.
Project-URL: Homepage, https://github.com/hoel-bagard/opencv-stubs
Project-URL: Bug Tracker, https://github.com/hoel-bagard/opencv-stubs/issues
Author: Bagard Hoel
License: MIT
License-File: LICENSE
Keywords: OpenCV,stubs
Classifier: Intended Audience :: Developers
Classifier: License :: OSI Approved :: MIT License
Classifier: Operating System :: OS Independent
Classifier: Programming Language :: Python
Classifier: Programming Language :: Python :: 3.8
Classifier: Programming Language :: Python :: 3.9
Classifier: Programming Language :: Python :: 3.10
Classifier: Programming Language :: Python :: 3.11
Classifier: Programming Language :: Python :: 3.12
Classifier: Programming Language :: Python :: 3.13
Classifier: Programming Language :: Python :: Implementation :: CPython
Requires-Python: >=3.8
Provides-Extra: opencv
Requires-Dist: opencv-python>=4.7.0; extra == 'opencv'
Provides-Extra: opencv-contrib
Requires-Dist: opencv-contrib-python>=4.7.0; extra == 'opencv-contrib'
Provides-Extra: opencv-headless
Requires-Dist: opencv-python-headless>=4.7.0; extra == 'opencv-headless'
